{
  "id": "slpa70",
  "display_name": "Total Duration of Apnea and Hypopnea (Non-Supine): Respiratory events with > 50% flow reduction and >= 4% oxygen desaturation during sleep in non-supine position from type III home sleep apnea test",
  "description": "Apnea and hypopnea events were not distinguished as separate event types during scoring. Both were classified as a respiratory event that required a 50% reduction in nasal flow signal and with >= 4% oxygen desaturation for at least 10 seconds.",
  "type": "numeric",
  "units": "seconds",
  "labels": [
    "ttldurah_po_ah5x4n_f1t3"
  ]
}
